pyarchitecture/__init__.py
pyarchitecture/config.py
pyarchitecture/squire.py
pyarchitecture/cpu/__init__.py
pyarchitecture/cpu/main.py
pyarchitecture/disks/__init__.py
pyarchitecture/disks/linux.py
pyarchitecture/disks/macOS.py
pyarchitecture/disks/windows.py
pyarchitecture/gpu/__init__.py
pyarchitecture/gpu/main.py
pyarchitecture/memory/__init__.py
pyarchitecture/memory/linux.py
pyarchitecture/memory/macOS.py
pyarchitecture/memory/windows.py
PyArchitecture-0.3.1.dist-info/LICENSE
PyArchitecture-0.3.1.dist-info/METADATA
PyArchitecture-0.3.1.dist-info/WHEEL
PyArchitecture-0.3.1.dist-info/entry_points.txt
PyArchitecture-0.3.1.dist-info/top_level.txt
PyArchitecture-0.3.1.dist-info/RECORD
