Metadata-Version: 2.1
Name: PyArchitecture
Version: 0.3.1
Summary: Python module to get kernel information via OS specific CLI commands
Author-email: Vignesh Rao <svignesh1793@gmail.com>
License: MIT License
Project-URL: Homepage, https://github.com/thevickypedia/PyArchitecture
Project-URL: Source, https://github.com/thevickypedia/PyArchitecture
Keywords: physical-drives,PyArchitecture
Classifier: License :: OSI Approved :: MIT License
Classifier: Programming Language :: Python :: 3
Classifier: Development Status :: 5 - Production/Stable
Classifier: Operating System :: OS Independent
Classifier: Topic :: System :: Hardware
Requires-Python: >=3.10
License-File: LICENSE
Provides-Extra: dev
Requires-Dist: pre-commit; extra == "dev"
